{
  "required": true,
  "minVersion": "0.8",
  "package": "com.cerbon.myths_of_the_sea.mixin",
  "compatibilityLevel": "JAVA_17",
  "mixins": [
    "LivingEntityMixin",
    "ServerPlayerMixin",
    "VillagerHostileSensorMixin",
    "items.EnchantmentHelperMixin",
    "items.LivingEntityMixinAbaia",
    "items.PlayerMixin",
    "kraken.EntityMixin"
  ],
  "client": [
    "items.HumanoidModelMixin",
    "items.ItemColorsMixin",
    "items.ItemInHandRendererMixin",
    "kraken.ClientPacketListenerMixin",
    "kraken.GuiMixin",
    "kraken.HumanoidModelMixinKraken",
    "kraken.LivingEntityRendererMixin",
    "test.TestMixin"
  ],
  "injectors": {
    "defaultRequire": 1
  }
}
